topsis/__init__.py
topsis/pro.py
Topsis_Mayank_102016012-0.0.4.dist-info/LICENSE.txt
Topsis_Mayank_102016012-0.0.4.dist-info/METADATA
Topsis_Mayank_102016012-0.0.4.dist-info/WHEEL
Topsis_Mayank_102016012-0.0.4.dist-info/entry_points.txt
Topsis_Mayank_102016012-0.0.4.dist-info/top_level.txt
Topsis_Mayank_102016012-0.0.4.dist-info/RECORD
